README.txt
setup.py
docs/HISTORY.txt
docs/INSTALL.txt
docs/LICENSE.GPL
docs/LICENSE.txt
plone/__init__.py
plone.mail.egg-info/PKG-INFO
plone.mail.egg-info/SOURCES.txt
plone.mail.egg-info/dependency_links.txt
plone.mail.egg-info/entry_points.txt
plone.mail.egg-info/namespace_packages.txt
plone.mail.egg-info/requires.txt
plone.mail.egg-info/top_level.txt
plone.mail.egg-info/zip-safe
plone/mail/__init__.py
plone/mail/configure.zcml
plone/mail/tests.py