Metadata-Version: 1.0
Name: plone.mail
Version: 0.1.1
Summary: A package containing a few methods to assist in handling and creating messages with encoded content
Home-page: http://svn.plone.org/svn/plone/plone.mail
Author: Alec Mitchell
Author-email: apm13@columbia.edu
License: GPL
Keywords: Mail Unicode Plone
Platform: UNKNOWN
